azutils/__init__.py
azutils/databricks/__init__.py
azutils/databricks/_client.py
azutils/databricks/_databricks.py
azutils/databricks/utils.py
test/__init__.py
test/conftest.py
test/test_databricks.py
azutils-0.1.2.dist-info/METADATA
azutils-0.1.2.dist-info/WHEEL
azutils-0.1.2.dist-info/top_level.txt
azutils-0.1.2.dist-info/RECORD
