Metadata-Version: 2.1
Name: azutils
Version: 0.1.2
Summary: Utilities for Azure
Home-page: https://github.com/gsy0911/azutils
Author: gsy0911
Author-email: yoshiki0911@gmail.com
License: MIT
Keywords: azure,databricks
Platform: UNKNOWN
Classifier: Programming Language :: Python :: 3
Classifier: Programming Language :: Python :: 3.6
Classifier: Programming Language :: Python :: 3.7
Classifier: Programming Language :: Python :: 3.8
Classifier: Development Status :: 3 - Alpha
Classifier: Operating System :: OS Independent
Classifier: Intended Audience :: Developers
Classifier: License :: OSI Approved :: MIT License
Requires-Python: >=3.6
Requires-Dist: cachetools
Requires-Dist: requests
Requires-Dist: seaborn
